quickclus/QuickClus.py
quickclus/__init__.py
quickclus/utils.py
tests/__init__.py
tests/quickclus_test.py
QuickClus-0.2.0.dist-info/LICENSE
QuickClus-0.2.0.dist-info/METADATA
QuickClus-0.2.0.dist-info/WHEEL
QuickClus-0.2.0.dist-info/top_level.txt
QuickClus-0.2.0.dist-info/RECORD
