Metadata-Version: 2.1
Name: QuickClus
Version: 0.2.0
Summary: UMAP + HDBSCAN for numeric and/or categorical variables
Home-page: https://github.com/aitorporcel/QuickClus
Author: Aitor Porcel Laburu
License: MIT
Platform: UNKNOWN
Classifier: Programming Language :: Python :: 3
Classifier: License :: OSI Approved :: MIT License
Classifier: Operating System :: OS Independent
Requires-Python: >=3.7
License-File: LICENSE
Requires-Dist: umap-learn (>=0.5.1)
Requires-Dist: numpy (>=1.20.2)
Requires-Dist: hdbscan (>=0.8.28)
Requires-Dist: numba (>=0.51.2)
Requires-Dist: pandas (>=1.3.4)
Requires-Dist: scikit-learn (>=1.0.2)
Requires-Dist: matplotlib (>=3.5.0)
Requires-Dist: optuna (>=2.10.0)
Requires-Dist: seaborn (>=0.11.2)
Requires-Dist: plotly (>=5.4.0)
